README.md
setup.py
cis_client/__init__.py
cis_client/cli.py
cis_client/exception.py
cis_client/run.py
cis_client/commands/__init__.py
cis_client/commands/cmd_cluster.py
cis_client/commands/cmd_content.py
cis_client/commands/cmd_ingest_point.py
cis_client/commands/cmd_job_status.py
cis_client/commands/cmd_profile.py
cis_client/commands/cmd_upload.py
cis_client/commands/cmd_workflow.py
cis_client/commands/printer.py
cis_client/commands/utils.py
cis_client/lib/__init__.py
cis_client/lib/base_http_client.py
cis_client/lib/chunk_upload.py
cis_client/lib/aaa/__init__.py
cis_client/lib/aaa/auth_client.py
cis_client/lib/aaa/token.py
cis_client/lib/cis_gateway/__init__.py
cis_client/lib/cis_gateway/aspera_client.py
cis_client/lib/cis_gateway/http_upload_client.py
cis_client/lib/cis_gateway/sftp_client.py
cis_client/lib/cis_north/__init__.py
cis_client/lib/cis_north/access_key_client.py
cis_client/lib/cis_north/content_client.py
cis_client/lib/cis_north/ingest_point_client.py
cis_client/lib/cis_north/jobs_client.py
cis_client/lib/cis_north/profile_client.py
cis_client/lib/cis_north/version_client.py
cis_client/lib/cis_north/workflow_client.py
cis_client/lib/cis_south/__init__.py
cis_client/lib/cis_south/cluster_client.py
udn_cis_client.egg-info/PKG-INFO
udn_cis_client.egg-info/SOURCES.txt
udn_cis_client.egg-info/dependency_links.txt
udn_cis_client.egg-info/entry_points.txt
udn_cis_client.egg-info/not-zip-safe
udn_cis_client.egg-info/requires.txt
udn_cis_client.egg-info/top_level.txt