Metadata-Version: 1.0
Name: udn-cis-client
Version: 1.5.7
Summary: UDN CIS client tool
Home-page: UNKNOWN
Author: Marian Horban
Author-email: mhorban@vidscale.com
License: UNKNOWN
Platform: UNKNOWN
